nlg_yongzhuo/__init__.py
nlg_yongzhuo/conf/__init__.py
nlg_yongzhuo/conf/logger_config.py
nlg_yongzhuo/conf/path_config.py
nlg_yongzhuo/data/__init__.py
nlg_yongzhuo/data/stop_words/__init__.py
nlg_yongzhuo/data/stop_words/stop_words.py
nlg_yongzhuo/data_preprocess/__init__.py
nlg_yongzhuo/data_preprocess/text_preprocess.py
nlg_yongzhuo/text_summarization/__init__.py
nlg_yongzhuo/text_summarization/extractive_sum/__init__.py
nlg_yongzhuo/text_summarization/extractive_sum/text_summary_merge.py
nlg_yongzhuo/text_summarization/extractive_sum/centroid_base/__init__.py
nlg_yongzhuo/text_summarization/extractive_sum/feature_base/__init__.py
nlg_yongzhuo/text_summarization/extractive_sum/feature_base/mmr.py
nlg_yongzhuo/text_summarization/extractive_sum/feature_base/text_pronouns.py
nlg_yongzhuo/text_summarization/extractive_sum/feature_base/text_teaser.py
nlg_yongzhuo/text_summarization/extractive_sum/feature_base/word_significance.py
nlg_yongzhuo/text_summarization/extractive_sum/graph_base/__init__.py
nlg_yongzhuo/text_summarization/extractive_sum/graph_base/textrank/__init__.py
nlg_yongzhuo/text_summarization/extractive_sum/graph_base/textrank/textrank.py
nlg_yongzhuo/text_summarization/extractive_sum/graph_base/textrank/textrank_gensim.py
nlg_yongzhuo/text_summarization/extractive_sum/graph_base/textrank/textrank_sklearn.py
nlg_yongzhuo/text_summarization/extractive_sum/graph_base/textrank/textrank_textrank4zh.py
nlg_yongzhuo/text_summarization/extractive_sum/nous_base/__init__.py
nlg_yongzhuo/text_summarization/extractive_sum/nous_base/keyword/__init__.py
nlg_yongzhuo/text_summarization/extractive_sum/nous_base/keyword/keyword_jieba.py
nlg_yongzhuo/text_summarization/extractive_sum/nous_base/keyword/keyword_word2vec.py
nlg_yongzhuo/text_summarization/extractive_sum/nous_base/lead_3/__init__.py
nlg_yongzhuo/text_summarization/extractive_sum/nous_base/lead_3/lead_3.py
nlg_yongzhuo/text_summarization/extractive_sum/topic_base/__init__.py
nlg_yongzhuo-0.0.4.dist-info/DESCRIPTION.rst
nlg_yongzhuo-0.0.4.dist-info/METADATA
nlg_yongzhuo-0.0.4.dist-info/RECORD
nlg_yongzhuo-0.0.4.dist-info/WHEEL
nlg_yongzhuo-0.0.4.dist-info/metadata.json
nlg_yongzhuo-0.0.4.dist-info/top_level.txt
